MANIFEST.in
README.rst
setup.py
bin/instayc
instayc/__init__.py
instayc/instayc.py
instayc.egg-info/PKG-INFO
instayc.egg-info/SOURCES.txt
instayc.egg-info/dependency_links.txt
instayc.egg-info/requires.txt
instayc.egg-info/top_level.txt
instayc.egg-info/zip-safe