Metadata-Version: 1.0
Name: instayc
Version: 0.1.1
Summary: Python tool for auto adding hacker news articles to    instapaper.
Home-page: http://github.com/jarodl/instayc
Author: Jarod Luebbert
Author-email: jarodluebbert@gmail.com
License: MIT
Platform: UNKNOWN
Classifier: Development Status :: 3 - Alpha
Classifier: Environment :: Console
Classifier: Intended Audience :: End Users/Desktop
Classifier: Natural Language :: English
Classifier: Operating System :: OS Independent
Classifier: Programming Language :: Python :: 2
Classifier: Topic :: Internet :: WWW/HTTP :: Dynamic Content :: CGI Tools/Libraries
Classifier: Topic :: Utilities
Classifier: License :: OSI Approved :: MIT License
